README.md
hi_tea.py
setup.py
Rilley.egg-info/PKG-INFO
Rilley.egg-info/SOURCES.txt
Rilley.egg-info/dependency_links.txt
Rilley.egg-info/entry_points.txt
Rilley.egg-info/requires.txt
Rilley.egg-info/top_level.txt